simplyprint_bambu/__init__.py
simplyprint_bambu/__main__.py
simplyprint_bambu/ams_utils.py
simplyprint_bambu/config.py
simplyprint_bambu/consts.py
simplyprint_bambu/container.py
simplyprint_bambu/files.py
simplyprint_bambu/printer.py
simplyprint_bambu/scheduled_jobs.py
simplyprint_bambu/supervisor.py
simplyprint_bambu/assets/restart-macos.sh
simplyprint_bambu/assets/restart-systemctl.sh
simplyprint_bambu/assets/restart-windows.ps1
simplyprint_bambu/assets/taskbar-icon-black.png
simplyprint_bambu/assets/taskbar-icon.ico
simplyprint_bambu/assets/update-macos.sh
simplyprint_bambu/assets/update-systemctl.sh
simplyprint_bambu/assets/update-windows.ps1
simplyprint_bambu/bambu_client/__init__.py
simplyprint_bambu/bambu_client/client.py
simplyprint_bambu/bambu_client/connection.py
simplyprint_bambu/bambu_client/consts.py
simplyprint_bambu/bambu_client/enums.py
simplyprint_bambu/bambu_client/events.py
simplyprint_bambu/bambu_client/protocol.py
simplyprint_bambu/bambu_client/ssl_ctx.py
simplyprint_bambu/bambu_client/utils.py
simplyprint_bambu/bambu_client/camera/__init__.py
simplyprint_bambu/bambu_client/camera/raw_jpeg.py
simplyprint_bambu/bambu_client/camera/rtsp.py
simplyprint_bambu/bambu_client/model/__init__.py
simplyprint_bambu/bambu_client/model/_base.py
simplyprint_bambu/bambu_client/model/_update_model.py
simplyprint_bambu/bambu_client/model/_validation.py
simplyprint_bambu/bambu_client/model/bind.py
simplyprint_bambu/bambu_client/model/event.py
simplyprint_bambu/bambu_client/model/liveview.py
simplyprint_bambu/bambu_client/model/root.py
simplyprint_bambu/bambu_client/model/security.py
simplyprint_bambu/bambu_client/model/system.py
simplyprint_bambu/bambu_client/model/info/__init__.py
simplyprint_bambu/bambu_client/model/info/module.py
simplyprint_bambu/bambu_client/model/print/__init__.py
simplyprint_bambu/bambu_client/model/print/ams.py
simplyprint_bambu/bambu_client/model/print/device.py
simplyprint_bambu/bambu_client/model/print/hms.py
simplyprint_bambu_lab-1.0.0b103.dist-info/METADATA
simplyprint_bambu_lab-1.0.0b103.dist-info/WHEEL
simplyprint_bambu_lab-1.0.0b103.dist-info/entry_points.txt
simplyprint_bambu_lab-1.0.0b103.dist-info/top_level.txt
simplyprint_bambu_lab-1.0.0b103.dist-info/RECORD
