Metadata-Version: 2.2
Name: simplyprint-bambu-lab
Version: 1.0.0b103
Summary: SimplyPrint Bambu Lab integration
Project-URL: Homepage, https://simplyprint.io
Project-URL: Get started, https://sp3d.io/bambu
Requires-Python: >=3.11
Requires-Dist: simplyprint-ws-client==1.0.1rc42
Requires-Dist: paho-mqtt>=2
Requires-Dist: hypercorn
Requires-Dist: quart
Requires-Dist: certifi
Requires-Dist: pystray
Requires-Dist: semver
Requires-Dist: avideostream; platform_machine == "armv7l"
Requires-Dist: opencv-python-headless; platform_machine != "armv7l"
Requires-Dist: curl_cffi
Requires-Dist: pydantic
Requires-Dist: pydantic-extra-types
Requires-Dist: apscheduler
Requires-Dist: lazy-object-proxy
Requires-Dist: setuptools[core]
Requires-Dist: pip>=25.3
